setup.py
spyne/__init__.py
spyne/_base.py
spyne/application.py
spyne/context.py
spyne/decorator.py
spyne/descriptor.py
spyne/error.py
spyne/evmgr.py
spyne/service.py
spyne/auxproc/__init__.py
spyne/auxproc/_base.py
spyne/auxproc/sync.py
spyne/auxproc/thread.py
spyne/client/__init__.py
spyne/client/_base.py
spyne/client/django.py
spyne/client/http.py
spyne/client/zeromq.py
spyne/client/twisted/__init__.py
spyne/const/__init__.py
spyne/const/ansi_color.py
spyne/const/http.py
spyne/const/xml.py
spyne/const/xml_ns.py
spyne/interface/__init__.py
spyne/interface/_base.py
spyne/interface/wsdl/__init__.py
spyne/interface/wsdl/defn.py
spyne/interface/wsdl/wsdl11.py
spyne/interface/xml_schema/__init__.py
spyne/interface/xml_schema/_base.py
spyne/interface/xml_schema/defn.py
spyne/interface/xml_schema/genpy.py
spyne/interface/xml_schema/model.py
spyne/interface/xml_schema/parser.py
spyne/model/__init__.py
spyne/model/_base.py
spyne/model/addtl.py
spyne/model/binary.py
spyne/model/complex.py
spyne/model/enum.py
spyne/model/fault.py
spyne/model/table.py
spyne/model/primitive/__init__.py
spyne/model/primitive/_base.py
spyne/model/primitive/datetime.py
spyne/model/primitive/network.py
spyne/model/primitive/number.py
spyne/model/primitive/spatial.py
spyne/model/primitive/string.py
spyne/model/primitive/xml.py
spyne/protocol/__init__.py
spyne/protocol/_base.py
spyne/protocol/_inbase.py
spyne/protocol/_outbase.py
spyne/protocol/csv.py
spyne/protocol/http.py
spyne/protocol/json.py
spyne/protocol/msgpack.py
spyne/protocol/xml.py
spyne/protocol/yaml.py
spyne/protocol/cloth/__init__.py
spyne/protocol/cloth/_base.py
spyne/protocol/cloth/to_cloth.py
spyne/protocol/cloth/to_parent.py
spyne/protocol/dictdoc/__init__.py
spyne/protocol/dictdoc/_base.py
spyne/protocol/dictdoc/hier.py
spyne/protocol/dictdoc/simple.py
spyne/protocol/html/__init__.py
spyne/protocol/html/_base.py
spyne/protocol/html/addtl.py
spyne/protocol/html/microformat.py
spyne/protocol/html/table/__init__.py
spyne_shopdev.egg-info/PKG-INFO
spyne_shopdev.egg-info/SOURCES.txt
spyne_shopdev.egg-info/dependency_links.txt
spyne_shopdev.egg-info/entry_points.txt
spyne_shopdev.egg-info/not-zip-safe
spyne_shopdev.egg-info/requires.txt
spyne_shopdev.egg-info/top_level.txt