Metadata-Version: 1.2
Name: spyne-shopdev
Version: 2.13.1
Summary: A transport and architecture agnostic rpc library that focuses on
Home-page: http://spyne.io
Author: Burak Arslan
Author-email: burak+package@spyne.io
Maintainer: Burak Arslan
Maintainer-email: burak+package@spyne.io
License: LGPL-2.1
Keywords: soap,wsdl,wsgi,zeromq,rest,rpc,json,http,msgpack,xml,django,pyramid,postgresql,sqlalchemy,twisted,yaml
Platform: UNKNOWN
Classifier: Programming Language :: Python
Classifier: Programming Language :: Python :: 2
Classifier: Programming Language :: Python :: 2.7
Classifier: Programming Language :: Python :: 3
Classifier: Programming Language :: Python :: 3.4
Classifier: Programming Language :: Python :: 3.5
Classifier: Programming Language :: Python :: 3.6
Classifier: Programming Language :: Python :: Implementation :: CPython
Classifier: Programming Language :: Python :: Implementation :: PyPy
Classifier: Operating System :: OS Independent
Classifier: Natural Language :: English
Classifier: Development Status :: 5 - Production/Stable
Classifier: Intended Audience :: Developers
Classifier: Topic :: Internet :: WWW/HTTP :: Dynamic Content
